linkt/__init__.py
linkt/_base_client.py
linkt/_client.py
linkt/_compat.py
linkt/_constants.py
linkt/_exceptions.py
linkt/_files.py
linkt/_models.py
linkt/_qs.py
linkt/_resource.py
linkt/_response.py
linkt/_streaming.py
linkt/_types.py
linkt/_version.py
linkt/py.typed
linkt/_utils/__init__.py
linkt/_utils/_compat.py
linkt/_utils/_datetime_parse.py
linkt/_utils/_logs.py
linkt/_utils/_proxy.py
linkt/_utils/_reflection.py
linkt/_utils/_resources_proxy.py
linkt/_utils/_streams.py
linkt/_utils/_sync.py
linkt/_utils/_transform.py
linkt/_utils/_typing.py
linkt/_utils/_utils.py
linkt/lib/.keep
linkt/resources/__init__.py
linkt/resources/files.py
linkt/resources/icp.py
linkt/resources/run.py
linkt/resources/signal.py
linkt/resources/task.py
linkt/resources/sheet/__init__.py
linkt/resources/sheet/entity.py
linkt/resources/sheet/schema.py
linkt/resources/sheet/sheet.py
linkt/types/__init__.py
linkt/types/csv_processing_status.py
linkt/types/entity_target_config_param.py
linkt/types/entity_type.py
linkt/types/file_list_params.py
linkt/types/file_list_response.py
linkt/types/file_retrieve_response.py
linkt/types/file_upload_params.py
linkt/types/file_upload_response.py
linkt/types/icp_create_params.py
linkt/types/icp_get_active_runs_response.py
linkt/types/icp_list_params.py
linkt/types/icp_list_response.py
linkt/types/icp_response.py
linkt/types/icp_update_params.py
linkt/types/ingest_task_config_param.py
linkt/types/profile_prompt_config_param.py
linkt/types/run_create_params.py
linkt/types/run_create_response.py
linkt/types/run_get_queue_params.py
linkt/types/run_get_queue_response.py
linkt/types/run_list_params.py
linkt/types/run_list_response.py
linkt/types/run_retrieve_response.py
linkt/types/search_task_config_param.py
linkt/types/sheet_create_params.py
linkt/types/sheet_export_csv_params.py
linkt/types/sheet_get_entities_params.py
linkt/types/sheet_get_entities_response.py
linkt/types/sheet_list_params.py
linkt/types/sheet_list_response.py
linkt_sdk-0.3.0.dist-info/METADATA
linkt_sdk-0.3.0.dist-info/WHEEL
linkt_sdk-0.3.0.dist-info/licenses/LICENSE
linkt_sdk-0.3.0.dist-info/RECORD
